Metadata-Version: 2.4
Name: mastodon-tag-case-corrector
Version: 1.0.0
Summary: Convert the display names of hashtags in a Mastodon instance to PascalCase
Home-page: https://codeberg.org/austinhuang/mastodon-tag-case-corrector
Author: Austin Huang
Author-email: im@austinhuang.me
License-Expression: Apache-2.0
Keywords: mastodon,moderation,hashtag
Classifier: Development Status :: 5 - Production/Stable
Classifier: Environment :: Console
Classifier: Programming Language :: Python :: 3.13
Classifier: Topic :: Communications
Classifier: Intended Audience :: Information Technology
License-File: LICENSE
Requires-Dist: python-dotenv
Requires-Dist: wordninja==2.0.*
Requires-Dist: requests==2.32.*
Dynamic: license-file
Dynamic: license-expression
